datadrop/__init__.py
datadrop/api_client.py
datadrop_cli_extralsc-0.1.2.dist-info/METADATA
datadrop_cli_extralsc-0.1.2.dist-info/WHEEL
datadrop_cli_extralsc-0.1.2.dist-info/entry_points.txt
datadrop_cli_extralsc-0.1.2.dist-info/licenses/LICENSE
datadrop_cli_extralsc-0.1.2.dist-info/RECORD
