Metadata-Version: 2.4
Name: datadrop_cli_extralsc
Version: 0.1.2
Summary: CLI tool for uploading and sharing files via datadrop.sh - like a pastebin for files
Project-URL: Homepage, https://datadrop.sh
Project-URL: Repository, https://github.com/extralsc/datadrop-cli
Project-URL: Issues, https://github.com/extralsc/datadrop-cli/issues
Author-email: Christopher S <chris@ceeglo.se>
License: MIT License
License-File: LICENSE
Keywords: cli,datadrop,file-sharing,pastebin,upload
Classifier: Development Status :: 4 - Beta
Classifier: Environment :: Console
Classifier: Intended Audience :: Developers
Classifier: Intended Audience :: End Users/Desktop
Classifier: License :: OSI Approved :: MIT License
Classifier: Operating System :: OS Independent
Classifier: Programming Language :: Python :: 3
Classifier: Programming Language :: Python :: 3.8
Classifier: Programming Language :: Python :: 3.9
Classifier: Programming Language :: Python :: 3.10
Classifier: Programming Language :: Python :: 3.11
Classifier: Programming Language :: Python :: 3.12
Classifier: Topic :: Internet :: File Transfer Protocol (FTP)
Classifier: Topic :: Utilities
Requires-Python: >=3.8
Requires-Dist: click>=8.1.7
Requires-Dist: requests>=2.31.0
